libraryTest/__init__.py
libraryTest/circle.py
libraryTest/rectangle.py
libraryTest-0.1.1.dist-info/METADATA
libraryTest-0.1.1.dist-info/WHEEL
libraryTest-0.1.1.dist-info/top_level.txt
libraryTest-0.1.1.dist-info/RECORD
