Metadata-Version: 2.1
Name: libraryTest
Version: 0.1.1
Summary: test description
Home-page: UNKNOWN
Author: UNKNOWN
Author-email: UNKNOWN
License: UNKNOWN
Platform: UNKNOWN
